LICENSE
README.md
setup.py
mclumi/Main.py
mclumi/Path.py
mclumi/__init__.py
mclumi/align/BundlePos.py
mclumi/align/Read.py
mclumi/align/Write.py
mclumi/align/__init__.py
mclumi/deduplicate/__init__.py
mclumi/deduplicate/monomer/Adjacency.py
mclumi/deduplicate/monomer/Build.py
mclumi/deduplicate/monomer/Build_test.py
mclumi/deduplicate/monomer/Cluster.py
mclumi/deduplicate/monomer/DedupBasic.py
mclumi/deduplicate/monomer/DedupGene.py
mclumi/deduplicate/monomer/DedupPos.py
mclumi/deduplicate/monomer/DedupPos_test.py
mclumi/deduplicate/monomer/DedupSC.py
mclumi/deduplicate/monomer/Directional.py
mclumi/deduplicate/monomer/MarkovClustering.py
mclumi/deduplicate/monomer/__init__.py
mclumi/external/UMItoolsSamMethods.py
mclumi/external/__init__.py
mclumi/fastq/Read.py
mclumi/fastq/Write.py
mclumi/fastq/__init__.py
mclumi/network/Adjacency.py
mclumi/network/CC.py
mclumi/network/Edge.py
mclumi/network/__init__.py
mclumi/plot/Graph.py
mclumi/plot/__init__.py
mclumi/trim/BCRuleOut.py
mclumi/trim/Filter.py
mclumi/trim/Fixed.py
mclumi/trim/Reader.py
mclumi/trim/SeqRuleOut.py
mclumi/trim/Template.py
mclumi/trim/UMIRuleOut.py
mclumi/trim/__init__.py
mclumi/util/Console.py
mclumi/util/Folder.py
mclumi/util/Hamming.py
mclumi/util/Number.py
mclumi/util/Reader.py
mclumi/util/Single.py
mclumi/util/Writer.py
mclumi/util/__init__.py
mclumix.egg-info/PKG-INFO
mclumix.egg-info/SOURCES.txt
mclumix.egg-info/dependency_links.txt
mclumix.egg-info/entry_points.txt
mclumix.egg-info/requires.txt
mclumix.egg-info/top_level.txt