Metadata-Version: 1.2
Name: mclumix
Version: 0.0.4
Summary: UMI de-duplication
Home-page: https://github.com/cribbslab; https://github.com/2003100127
Author: Jianfeng Sun
Author-email: jianfeng.sun@ndorms.ox.ac.uk
License: MIT
Keywords: pip,mclumi
Platform: any
Requires-Python: >3.6
